zrxp-2.0.6.dist-info/METADATA
zrxp-2.0.6.dist-info/WHEEL
zrxp-2.0.6.dist-info/licenses/LICENSE
zrxp/__init__.py
zrxp/_core.cp314t-win_amd64.pyd
zrxp/_core.pyi
zrxp/data.py
zrxp/exceptions.py
zrxp/py.typed
zrxp/reader.py
zrxp/writer.py
zrxp-2.0.6.dist-info/RECORD
